{
    "3203687268": "3203687268",
    "9172917575": "DAYAN",
    "8778388464": "8778388464",
    "2013485733": "County Bettty Union",
    "7325423400": "Tinton Deana Web X140",
    "4253729157": "Ing Calida",
    "5627356555": "123 Amip Liz",
    "3104417710": "Island Demetre Architect Staten",
    "8004212110": "520 Bank Of America",
    "8585687031": "Api Brett Odd Jam",
    "9086872333": "Lawyer Bruce Radowitz",
    "9084510665": "Linden Bob Realtor",
    "2017500200": "Dist Beauty And Ugly",
    "2018762788": "Ng China Contru Tion Prefab",
    "5184858953": "Certicate Apply For",
    "6063303850": "Broker Become A Custom",
    "7189536480": "Lawyer Al Fogel",
    "3474211659": "Assistant April Law",
    "8774884224": "Rent Car 2 Go",
    "5029553901": "Squad Data Recovery Geek",
    "7724488128": "Skilman Brunner",
    "7187887912": "Betesh Dependable Isaac",
    "5138550406": "12 Caleb Hurd Lawyer",
    "6099525106": "Print Deinde Jim 2 To 5 Pm Blue",
    "7323939194": "Mtg Arnol Lubin Loan Elayne Epa",
    "7329026090": "Epa Aldo Insurane",
    "7149551560": "Legends Bill Insurance Epa",
    "9737980952": "EPA Bob Strategic Insurance",
    "9732905779": "Lease Dave Fischer",
    "6468334511": "Reporting Accion Carmen Credit",
    "9176899009": " Anustup Dutta",
    "7183764740": "Jewelry David Rudy",
    "7409198469": "300 David Website",
    "7326687001": " Andrew Lsrp",
    "5128613309": "aging anti",
    "8004421902": "standard american",
    "8009379977": "Country Call T Mobile From International",
    "5127170185": "Aging Call In Conference Sara Anti",
    "6093475630": "Tax Candace Atlantic City",
    "7322874364": "Accountant Dassi",
    "5166279300": "Santander Ariele",
    "8562912885": "Survey Angela TD",
    "2127104600": "X2021 Damian Robertet",
    "9737488980": "X898 Berje Fragrance Oshea",
    "7323630708": "Title Adina Gold Crest",
    "9084034167": "Builder Bob",
    "8457504764": "Chemist Brian Mulany",
    "3632797096": "Stamping Anna Label Hot",
    "1054527072": "Lotion Cossed Junh-no Base",
    "7328503598": "Loan Christine Wells Fargo",
    "8006066969": "Bh",
    "2124010800": "Complaint comte",
    "9085668968": "Alan",
    "9733092550": "Hvac Ben",
    "5622190898": "Fragrance Anhui Micro delivery",
    "8002821451": "Chinrse",
    "5619391900": "Ingredients Chris Oleo Fine France And Tech Self",
    "2018839707": "Ig Broker Century",
    "8668662432": "Delete Cheap",
    "6036735050": "Candles Arlene",
    "7183397224": "Virus Cryprto Prevent Serber",
    "3159493107": "Brian Pick Up",
    "8003833812": "Renew Bond",
    "8664998008": "Nu Att",
    "7183364303": "Citi Demitre",
    "7344747497": "Arielle Amcor",
    "7153841176": "Beth Weber",
    "2243025373": "Filling American Blending",
    "7323705300": "Nj Accountant",
    "8455472092": "Carl Abstract Fragrance",
    "2067178421": "Aws",
    "7076652100": "Cashing Check",
    "7184412470": "3_28 Chabbad Donate",
    "3472813967": "Shad Chaya Maslaton",
    "6084264106": "Hall Danielle",
    "6504776732": "Illustrator Arthur Lin",
    "9176742358": "Sutton Rabbi",
    "6105478013": "F Alexandra Derita Graphic 28",
    "8778864318": "Filler Adam 216 Us Continental Liquid",
    "7733225607": "Pouch Amy",
    "3729554367": "Pouch Carina Lin",
    "7326642169": "Gindi Avraham",
    "8883184093": "Honda Dch",
    "3104856833": "Rep Dds Trucking",
    "7188342200": "Tax Advocate",
    "8002512522": "Almar Allen R Ash",
    "7132421956": "Loan Deposit Capital",
    "8003640045": "Extra A Li Fung Co Added",
    "7188337616": "Skin David Viro",
    "2143126119": "Aafes Adriana",
    "1706764928": "250 Ann",
    "9173977122": "Chaberim",
    "7183362200": "Catering Chayat",
    "9082267607": "Opra Andrew South Plainfield",
    "7327352880": "Brownstone Darryl Stephanson",
    "2128241146": "Ronnie Adam Hard Money From",
    "3128246498": "Echo Brian",
    "7328530271": "Mai Alsheny Appraisal X101",
    "9088792424": "1500 Appraiser Mai Bob",
    "9084703339": "Sba Andy Glatz Lender",
    "6315269065": "Closeouts Andrew",
    "8886448314": "360 Capital",
    "3852139963": "Loan Dan From Lendio Ideal",
    "8003423377": "Complaint Consumer Grid Con Edison",
    "5168585047": "Money Camran Hard",
    "7325681266": "ingredients Dan Upichem Chemcals",
    "4238378800": "Chemicals Colonial",
    "9732762698": "Hvac Anna",
    "8556359696": "Bank Call",
    "9738276800": "Franklin Caffrey Pam And Associates Survey",
    "4796572819": "Cards Cody Business Credit",
    "5184538199": "IRS David",
    "8885645160": "Insurance Cheap",
    "7184357585": "general attorney",
    "7182980325": "Supervisor Charles Naca Ray",
    "9085781880": "Contractor David Fabbo Meet Up",
    "8009359935": "Express Ali",
    "6169777900": "Lender David Northwind",
    "2018586055": "Lien Bayone Tarrence Meloy",
    "7185698563": "Lawyer Alan Sasson",
    "5304365630": "Loan Avi Hard",
    "2018586357": "Camille Bayone Tax Lien",
    "7324946800": "Weichert Andy Mtg Broker",
    "9087533214": "Iien Dave South Plainfield Tax",
    "3473095260": "Jenate Aaron",
    "9176699617": "Plumber Bobby",
    "6097520991": "Miles Coxcorner Realtor Empty Land 60",
    "6468256300": "Urologist Christopher Kelly",
    "9617787788": "Azaasad",
    "7325837474": "Law Cleary Alfr G Joe Demarco Bayonne",
    "8563148287": "Gutters All Star",
    "7157204326": "Mason Ap",
    "6099841742": "Enviromental Dep",
    "9175326395": "Cabinet D Singh Kitchen",
    "8007217360": "Culligan",
    "7328943686": "Lawyer Botton Leo",
    "8604324506": "Rcn David Young",
    "7184127777": "Warehouse Boris Hard Money",
    "8006592955": "Back Covid 19 Sba Call",
    "7183779700": "Hole Bagel",
    "3123244960": "Deliverr",
    "6465017722": "neurology concusion center",
    "7323205275": "Haim Andrew Lsrp",
    "3472160140": "Harari Albert",
    "7325318700": "julie albaum dentist",
    "6097078469": "nj brian courier",
    "9177216297": "Man Derick Handy",
    "9319801447": "Plainfield Angel Contractor South",
    "3022880670": "bgtwodel",
    "8886872277": "membership aarp",
    "7578970364": "Ok Architect",
    "8622580357": "Mold Chemical For Smell Odor Drain",
    "8624382789": "Plumber Charlie",
    "9736841633": "ironworks d jonge",
    "7328506983": "rd danielle 912 deal",
    "7328865751": "prime connie insurance",
    "9738000409": "lsrp david deghetto field",
    "8443621625": "market dealson",
    "2158246436": "doctor dent",
    "9293109609": "Bawabe Abraham Safdie",
    "7185221001": "Plumbing Carrol",
    "5207773360": "Machines Bush",
    "2096036399": "Supervalu Delivery",
    "6318459780": "Dist Bilo",
    "8007565005": "Works Bath And Body",
    "9172098531": "ESSES BELLA",
    "2062664064": "Dept Amazon Legal",
    "6099843444": "Epa Diane Dowe Wetland Flood",
    "8669667226": "Dept Attorney General Fl Fraud",
    "6092785175": "Loan Darryl Njra",
    "6097771398": "Njdep Attwood Davis",
    "5062142959": "Epa Arpad Hydrogeologist",
    "9085084324": "Epa Richerd Axis Insurance",
    "7328188698": "Lsrp Bill",
    "9732565330": "Specialist Berger Sba",
    "6468375557": "Rosmarin David",
    "7186270174": "Highway Borus Td Kings",
    "6782632308": "hardware credit card",
    "7044893578": "bytestand",
    "8009086679": "Through Asbestos Walk",
    "8662450783": "X1511 Carmen Accion",
    "1243400200": "Bulk Delta Labs Australia",
    "8002301284": "Dollar Amex Heidi Match Dollar For",
    "9166044892": "6000 Danny",
    "7189983146": "Chase Boris Business Relationship Manager",
    "5174100928": "Component Colin Philips",
    "8778888676": "Gilbert Blue Printer",
    "2019534956": "Slab Dan Obar Depressure Sub",
    "3217620699": "Web Ahmed",
    "6462477575": "Book Albert Betesh",
    "2487900278": "40 Brittany Brooks Graphic Dezigner F",
    "2124611990": "Investor David",
    "7179728300": "Bfvr",
    "8325643141": "Rachel Clarity Fragrance",
    "7185060500": "Mr halpern Cope",
    "8004682274": "Engagement CosmoProf Show Janice Olson",
    "2403453268": "9 Dan Credit Cards 7",
    "6155957673": "Dollar Dave Parone",
    "6108132862": "Aws Chris Cloud Nexa",
    "8476797010": "Pankow Allen Hirshfield",
    "8003272177": "Amex",
    "8886069716": "Wire Citi",
    "3477308015": "Leal Aharon",
    "6054907825": "Angela Hohn Part",
    "2152313820": "Bianca Verizon",
    "6092349584": "Bill Moran Penerco",
    "7176364893": "Dewolf Amy",
    "6146523599": "Cohen Benny",
    "7186767781": "Restaurant Chinese",
    "9732457201": "Dewolf Chemicals",
    "2106987899": "Heb Denise",
    "7183125500": "Brooklyn Dhl",
    "7183834488": "Filler Cosco",
    "5803552182": "Fill Cosmetic Specialty Lab",
    "8884323183": "203 Colleen2 Oz Toillete Only",
    "7342224678": "Hosting A2",
    "5629419800": "Ltl Dd Delivery",
    "2037433884": "102 Dan Coakley Machine",
    "7144107033": "Elite Conference 714",
    "7183369100": "Ur Denil",
    "7188591110": "Chantily",
    "4794012000": "101 Bert",
    "6468334533": "Accion Carolina",
    "8662161072": "Amazon",
    "9423637690": "China Conveyor Belt",
    "9179246670": "Technacian Abdu Rahmen It",
    "9737572303": "Brownstone",
    "7185045625": "Locksmith Car Key",
    "7184367373": "Snapp Chubbie",
    "7149856000": "X223 Cresase Stg Usa Pick Up",
    "9736283341": "Holdings Carl Eckalrt Linden Properties",
    "3364421326": "Penco Dan Darnell",
    "5184747080": "Utilities Commision",
    "9147479393": "David Alan Harris Lawyer From Earl",
    "9294660300": "Remediate Alana Miller Regenesis",
    "7182158500": "Mortgage Ark",
    "7727744681": "Connect Construct",
    "2153376213": "Chemicals Chelsea Univar",
    "6466652159": "Estate Benny Real"
}